{
  "area": "Cardiologia",
  "assunto": "Edema Agudo de Pulmao",
  "espacamento": "normal",
  "criterios": "",
  "criterios_tom": "neutro",
  "dicas": "",
  "dicas_tom": "neutro",
  "exames": "",
  "exames_tom": "neutro",
  "prescricao": "## Edema Agudo de Pulmão Não Hipertensivo\n\n### Orientações ao Prescritor\n\n- É necessário diagnóstico rápido e avaliação do nível de consciência para optar pela melhor forma de ventilação;\n- Garantir estabilidade hemodinâmica;\n- Diagnosticar a causa base e tratá-la de maneira adequada;\n- Diagnosticar o EAP para tratamento adequado de sua causa:\n- Ex.: Revascularização, DAPT e Heparina no caso de IAM; anticoagulação nos casos de TEP.\n- Em caso de taquiarritmia: Empregar cardioversão elétrica ou química (exceto se o ritmo for taquicardia sinusal). No EAP e na estenose mitral, o uso de betabloqueador é indicado;\n- Em caso de bradiarritmia: Avaliar necessidade de marca-passo provisório.\n\n#### Tratamento farmacológico:\n\n- Morfina: O uso rotineiro n ão é recomendado, dado os riscos inerentes ao medicamento:\n- Utilizar na menor dose efetiva apenas para alívio da ansiedade e melhora da sensação de dispneia.\n- Vasopressores: Indicados para manter PAM > 65 e PAS > 90 mmHg, se choque associado;\n- Vasodilatadores: Indicados em pacientes normotensos, para reduzir a pós-carga, facilitar o trabalho cardíaco e diminuir a pressão atrial esquerda e pulmonar;\n- Inotrópicos: Indicados em casos de d isfunção sistólica associada ou edema agudo de pulmão cardiogênico:\n- Devem ser administrados com cautela em pacientes hipotensos, pois podem causar redução da PA pela diminuição da pós-carga. Associar a vasopressores se PAS < 90 mmHg ou PAM < 65 mmHg.\n\n### Dieta e Hidratação\n\n- Dieta zero (até melhora da dispneia e retorno da consciência).\n- SF 0,9% 20-30 mL/kg/dia, conforme o grau de hidratação e balanço hídrico do paciente:\n- SF 0,9% 30 mL/kg, em bólus, em caso de hipotensão.\n\n### Tratamento Farmacológico\n\nEscolha uma das classes ou associe-as conforme necessidade clínica.\n\n- Furosemida (20 mg/2 mL): 0,5-1 mg/kg EV, 6/6 horas até melhora da congestão.\n\n#### Classe B:\n\nControle da dor, ansiedade e sensação da dispneia.\n\n- Morfina (10 mg/1 mL): 1 ampola + 9 mL de SF 0,9% (concentração: 1 mg/mL). Administrar 2-5 mg EV a cada 5-30 minutos, até obter conforto.\n- Noradrenalina (1 mg/mL): 20 mL + SG 5% 80 mL (200 microgramas/mL) 0,05-0,1 micrograma/kg/minuto EV, conforme resposta (dose máxima: 0,5 micrograma/kg/minuto; ~ 40 mL/hora);\n- Dobutamina (250 mg/20 mL): 20 mL + SG 5% 230 mL (1.000 microgramas/mL) 1-2,5 microgramas/kg/minuto EV conforme resposta (dose máxima: 15-30 microgramas/kg/minuto);\n- Dopamina (50 mg/10 mL): 50 mL + SF 0,9% 200 mL (1 mg/mL) 1-25 microgramas/kg/minuto EV em BI, como alternativa à Noradrenalina .\n\nVasodilatadores endovenosos.\n\n- Nitroglicerina (50 mg/10 mL): 10 mL + SG 5% 240 mL (200 microgramas/mL) 5-10 microgramas/minuto EV em BI (1,5-3,0 mL/hora), com aumentos de 10 microgramas/minuto a cada 3-5 minutos (dose máxima: 100-200 microgramas/minuto ou 60 mL/hora);\n- Nitroprussiato de sódio (50 mg/2 mL): 2 mL + SG 5% 248 mL (200 microgramas/mL) 0,25-0,5 micrograma/kg/minuto EV em BI com aumentos de 0,5 micrograma (dose máxima: 8-10 microgramas/kg/minuto).\n\n#### Classe E:\n\nBetabloqueadores venosos.\n\n- Metoprolol (1 g/mL – ampola de 5 mg): 5 mg EV em 1-2 mg/minuto; pode ser repetido em intervalos de 5 minutos, máximo de 15 mg no total;\n- Esmolol (250 mg/mL e 10 mg/mL – ampolas com 10 mL): Diluição (250 mg/mL): 10 mL + 250 mL de SG 5%, SF 0,9% ou ringer lactato. Dose de ataque: 0,5 mg/kg EV durante 1 minuto e, a seguir, 0,05 mg/kg/minuto durante 4 minutos. Dose de manutenção: 50-200 microgramas/kg/minuto EV.\n\n### Profiláticos e Sintomáticos\n\n#### Analgésicos e antitérmicos:\n\n- Dipirona sódica (500 mg/mL): 1-2 g EV até de 4/4 horas (dose máxima: 5 g em 24 horas);\n- Dipirona sódica gotas (500 mg/mL): 20-40 gotas VO até de 4/4 horas;\n- Dipirona sódica 500-1.000 mg VO até de 4/4 horas;\n- Paracetamol gotas (200 mg/mL): 35-55 gotas VO até de 6/6 horas;\n- Paracetamol 500-750 mg VO até de 6/6 horas.\n\n#### Antieméticos:\n\n- Metoclopramida (10 mg/2 mL): 10 mg EV, diluída em água destilada, até de 8/8 horas;\n- Metoclopramida (4 mg/mL): 50 gotas VO de 8/8 horas;\n- Metoclopramida 10 mg VO de 8/8 horas;\n- Bromoprida (10 mg/2 mL): 10 mg EV de 8/8 horas;\n- Bromoprida (4 mg/mL): 1-3 gotas/kg VO de 8/8 horas.\n\n#### Proteção gástrica:\n\n- Omeprazol (40 mg/10 mL): 20-40 mg VO/EV de 24/24 horas, pela manhã;\n- Pantoprazol sódico 20-40 mg VO de 24/24 horas, em jejum;\n- Pantoprazol sódico (40 mg/10 mL): 40 mg EV de 24/24 horas.\n- Enoxaparina 1 mg/kg (ou 40 mg) SC de 24/24 horas; se > 75 anos de idade, corrigir para 0,75 mg/kg SC de 24/24 horas. Contraindicada em pacientes com ClCr < 30 mL/minuto;\n- Heparina não fracionada 5.000 unidades SC de 8/8 ou 12/12 horas. Contraindicada se: Plaquetometria < 100.000/mm 3 ou INR > 1,5.\n\n### Cuidados\n\n- Cabeceira elevada entre 60° e 90º.\n- Ventilação mecânica não invasiva com máscara facial (CPAP inicial de 6-8 cmH 2 O; aumentar conforme necessidade para controle do quadro):\n- Oxigênio sob máscara com reservatório a 10-15 L/minuto, para manter saturação > 92%, até a disponibilidade de VNI.\n- Pacientes com síndrome do estresse respiratório agudo moderada a grave necessitam, na maioria dos casos, de ventilação mecânica:\n- Para mais informações, acesse Intubação orotraqueal;\n- Nos casos de IOT + VM, manter sedação adequada (RASS entre 0 e -2).\n- Antibioticoterapia de acordo com o foco provável (em casos de síndrome do estresse respiratório agudo secundária à sepse ). Iniciar na primeira hora, após a coleta das hemoculturas.\n- Glicemia capilar de 2/2 horas a 4/4 horas.\n- Glicose hipertônica a 50%: 40 mL EV, se HGT < 70 mg/dL.\n- Insulina regular 100 unidades (1 mL) + SF 0,9% 99 mL (solução: 1 unidade/mL) EV, em BIC, a critério médico.\n- Instalar circuito de PVC, a critério médico.\n- Monitorização cardíaca contínua, oximetria de pulso e PA (não invasiva ou invasiva, conforme a necessidade de drogas vasoativas).\n- Instalar sonda vesical de demora e monitorar diurese.\n\n### Edema Agudo de Pulmão Hipertensivo\n\n### Orientações ao Prescritor\n\n- Estabilização hemodinâmica;\n- Emergência hipertensiva: Reduzir a PA em até 25% na 1ª hora; alvo de 160 x 100-110 mmHg em 2 a 6 horas e de 135 x 85 mmHg em 24 a 48 horas;\n- Sempre que possível, associar ventilação não invasiva;\n- Promover vasodilatação e redução da resistência periférica (pós-carga);\n- Promover venodilatação e redução do retorno venoso (pré-carga).\n\n#### Tratamento farmacológico:\n\n- Morfina: N ão é recomendado seu uso rotineiro, dados os riscos inerentes ao medicamento:\n- Utilizar na menor dose efetiva, apenas para alívio da ansiedade e melhora da dispneia.\n- Nitroprussiato de sódio: U so cauteloso em pacientes com insuficiência renal, devido ao risco de intoxicação por cianeto. Idealmente, manter o uso por menos de 48 horas;\n- Nitroglicerina: Ideal para pacientes com EAP secundário à síndrome coronariana aguda. Atenção à possibilidade de taquifilaxia com o uso contínuo.\n\nQuais os suportes não invasivos indicados para ventilação no EAP cardiogênico?\n\n### Dieta e Hidratação\n\n- Dieta zero (até melhora da dispneia e retorno da consciência).\n\n### Tratamento Farmacológico\n\nEscolha uma das classes ou associe-as conforme necessidade clínica.\n\n#### Diurético de alça:\n\n- Furosemida (20 mg/2 mL): 0,5-1 mg/kg EV, até melhora da congestão.\n\n#### Classe B:\n\n#### Controle da dor, ansiedade e sensação da dispneia:\n\n- Morfina (10 mg/1 mL): 1 ampola + 9 mL de SF 0,9% (concentração: 1 mg/mL). Administrar 2-5 mg EV a cada 5-30 minutos, até obter conforto.\n- Nitroglicerina (50 mg/10 mL): 10 mL + SG 5% 240 mL (200 microgramas/mL) 5-10 microgramas/minuto EV em BI (1,5-3,0 mL/hora), com aumentos de 10 microgramas/minuto a cada 3-5 minutos (dose máxima: 100-200 microgramas/minuto ou 60 mL/hora);\n- Nitroprussiato de sódio (50 mg/2 mL): 2 mL + SG 5% 248 mL (200 microgramas/mL) 0,25-0,5 micrograma/kg/minuto EV em BI com aumentos de 0,5 micrograma (dose máxima: 8-10 microgramas/kg/minuto).\n\n#### Classe D:\n\nVasodilatadores orais.\n\n- Captopril (2,5-50 mg/comprimido): 25-50 mg VO até de 8/8 horas;\n- Losartana (25-50 mg/comprimido): 25-100 mg VO até de 12/12 horas;\n- Hidralazina (25-50 mg/comprimido): 25-100 VO de 8/8 horas a 6/6 horas.\n\n### Profiláticos e Sintomáticos\n\n#### Analgésicos e antitérmicos:\n\n- Dipirona sódica (500 mg/mL): 1-2 g EV até de 4/4 horas (dose máxima: 5 g em 24 horas);\n- Dipirona sódica gotas (500 mg/mL): 20-40 gotas VO até de 4/4 horas;\n- Dipirona sódica 500-1.000 mg VO até de 4/4 horas;\n- Paracetamol gotas (200 mg/mL): 35-55 gotas VO até de 6/6 horas;\n- Paracetamol 500-750 mg VO até de 6/6 horas.\n\n#### Antieméticos:\n\n- Metoclopramida (10 mg/2 mL): 10 mg EV, diluída em água destilada, até de 8/8 horas;\n- Metoclopramida (4 mg/mL): 50 gotas VO de 8/8 horas;\n- Metoclopramida 10 mg VO de 8/8 horas;\n- Bromoprida (10 mg/2 mL): 10 mg EV de 8/8 horas;\n- Bromoprida (4 mg/mL): 1-3 gotas/kg VO de 8/8 horas.\n\n#### Para proteção gástrica:\n\n- Omeprazol (40 mg/10 mL): 20-40 mg VO/EV de 24/24 horas, pela manhã;\n- Pantoprazol sódico 20-40 mg VO de 24/24 horas, em jejum;\n- Pantoprazol sódico (40 mg/10 mL): 40 mg EV de 24/24 horas.\n\n### Cuidados\n\n- Ventilação mecânica não invasiva com máscara facial (CPAP de 6-8 cmH 2 O, inicialmente):\n- Oxigênio sob máscara a 5-10 L/minuto, para manter saturação > 92%, até disponibilidade de VNI.\n- Glicemia capilar de 2/2 horas a 4/4 horas.\n- Glicose hipertônica a 50%, 40 mL EV, se HGT < 70.\n- Insulina regular 100 unidades (1 mL) + SF 0,9% 99 mL (solução: 1 unidade/mL), EV, em BIC, a critério médico.\n- Instalar circuito de PVC, a critério médico.\n- Monitorização cardíaca contínua, oximetria de pulso e PA não invasiva.\n- Sonda vesical de demora e monitorização de diurese.\n- Cabeceira elevada entre 60° e 90 o .",
  "prescricao_tom": "neutro",
  "prescricao_copiavel": true,
  "prescricao_copia": "",
  "prescricao_copiar_rotulo": "Copiar prescrição",
  "atualizado_em": "2026-02-05"
}